Routing_flet/404.py
Routing_flet/ViewPage.py
Routing_flet/__init__.py
Routing_flet/cli.py
Routing_flet/config.py
Routing_flet/index.py
Routing_flet/main.py
Routing_flet/route.py
Routing_flet-0.0.4.dist-info/LICENSE
Routing_flet-0.0.4.dist-info/METADATA
Routing_flet-0.0.4.dist-info/WHEEL
Routing_flet-0.0.4.dist-info/entry_points.txt
Routing_flet-0.0.4.dist-info/top_level.txt
Routing_flet-0.0.4.dist-info/RECORD
