Metadata-Version: 2.1
Name: Routing-flet
Version: 0.0.4
Summary: Esta es la descripcion de mi paquete
Home-page: https://github.com/Dxsxsx/Routing_flet
Download-URL: https://github.com/Dxsxsx/Routing_flet
Author: Dxsxsx
Project-URL: Bug Tracker, https://github.com/Dxsxsx/Routing_flet/issues
Keywords: python web template,web application,development
Classifier: License :: OSI Approved :: MIT License
Classifier: Programming Language :: Python :: 3
Classifier: Operating System :: OS Independent
Requires-Python: >=3.6
License-File: LICENSE
Requires-Dist: typer[all]
Requires-Dist: flet
